box_ai_agents_toolkit/__init__.py
box_ai_agents_toolkit/box_api_ai.py
box_ai_agents_toolkit/box_api_collaborations.py
box_ai_agents_toolkit/box_api_docgen.py
box_ai_agents_toolkit/box_api_docgen_template.py
box_ai_agents_toolkit/box_api_file.py
box_ai_agents_toolkit/box_api_folder.py
box_ai_agents_toolkit/box_api_groups.py
box_ai_agents_toolkit/box_api_metadata_template.py
box_ai_agents_toolkit/box_api_search.py
box_ai_agents_toolkit/box_api_shared_links.py
box_ai_agents_toolkit/box_api_tasks.py
box_ai_agents_toolkit/box_api_users.py
box_ai_agents_toolkit/box_api_util_classes.py
box_ai_agents_toolkit/box_api_util_generic.py
box_ai_agents_toolkit/box_api_util_http.py
box_ai_agents_toolkit/box_api_weblink.py
box_ai_agents_toolkit/box_auth_callback.py
box_ai_agents_toolkit/box_authentication.py
box_ai_agents_toolkit/py.typed
box_ai_agents_toolkit-0.1.3.dist-info/METADATA
box_ai_agents_toolkit-0.1.3.dist-info/WHEEL
box_ai_agents_toolkit-0.1.3.dist-info/licenses/LICENSE
box_ai_agents_toolkit-0.1.3.dist-info/RECORD
