Metadata-Version: 2.4
Name: box-ai-agents-toolkit
Version: 0.1.3
Summary: A python library for building AI agents for Box
Project-URL: Repository, https://github.com/box-community/box-ai-agents-toolkit.git
Project-URL: Issues, https://github.com/box-community/box-ai-agents-toolkit/issues
Author-email: Box Developer Relations <devrel@box.com>
Maintainer-email: Box Developer Relations <devrel@box.com>
License-Expression: MIT
License-File: LICENSE
Keywords: agent,ai,box,box ai,box ai api,box api,box.com,library,toolkit
Classifier: Development Status :: 4 - Beta
Classifier: Programming Language :: Python
Requires-Python: >=3.11
Requires-Dist: box-sdk-gen>=1.17.0
Requires-Dist: python-dotenv>=1.0.1
